[{"url":"/weibo?q=%23%E6%9D%A8%E4%B8%9E%E7%90%B3%E6%9D%8E%E8%8D%A3%E6%B5%A9%E7%BB%88%E4%BA%8E%E8%A7%81%E9%9D%A2%E4%BA%86%23&Refer=top","text":"杨丞琳李荣浩终于见面了","count":6828096},{"url":"/weibo?q=%E5%BC%A0%E9%A6%A8%E4%BA%88%20%E6%80%8E%E4%B9%88%E5%A5%B3%E4%BA%BA%E4%B8%AD%E6%80%A7%E4%B8%80%E7%82%B9%E5%B0%B1%E8%A6%81%E8%A2%AB%E8%AE%AE%E8%AE%BA&Refer=top","text":"张馨予 怎么女人中性一点就要被议论","count":6780776.399999999},{"url":"/weibo?q=%23%E8%82%9B%E6%8B%AD%E5%AD%90%E5%8F%97%E9%87%87%E8%80%85%E8%AE%B2%E8%BF%B0%E9%87%87%E6%A0%B7%E8%BF%87%E7%A8%8B%23&Refer=top","text":"肛拭子受采者讲述采样过程","count":5057313.6},{"url":"/weibo?q=%23%E9%99%88%E5%BE%B7%E5%AE%B9%E9%80%80%E5%87%BA%E6%88%91%E5%B0%B1%E6%98%AF%E6%BC%94%E5%91%98%23&Refer=top","text":"陈德容退出我就是演员","count":5009869.2},{"url":"/weibo?q=%E6%9D%9C%E6%B7%B3%20%E6%98%AF%E5%8A%A8%E4%BD%9C%E7%9A%84%E9%97%AE%E9%A2%98%E8%BF%98%E6%98%AF%E6%88%91%E7%9A%84%E9%97%AE%E9%A2%98&Refer=top","text":"杜淳 是动作的问题还是我的问题","count":4706552.399999999},{"url":"/weibo?q=%23%E7%99%BD%E5%B2%A9%E6%9D%BE%E8%AF%B4%E9%98%B2%E7%96%AB%E6%98%AF%E5%A4%A7%E4%BA%8B%E4%BD%86%E8%A1%8C%E4%B8%BA%E4%B8%8D%E8%83%BD%E7%A0%B4%E5%BA%95%E7%BA%BF%23&Refer=top","text":"白岩松说防疫是大事但行为不能破底线","count":4164669.5999999996},{"url":"/weibo?q=%23%E7%8E%8B%E7%90%B3%E5%84%BF%E5%AD%90%23&Refer=top","text":"王琳儿子","count":4088054.4000000004},{"url":"/weibo?q=%23%E5%BC%A0%E4%BC%AF%E7%A4%BC%E7%A7%B0%E4%BB%8A%E5%86%AC%E7%96%AB%E6%83%85%E6%9C%89%E6%9C%9B3%E6%9C%88%E5%88%9D%E7%96%AB%E9%9C%BE%E5%B0%BD%23&Refer=top","text":"张伯礼称今冬疫情有望3月初疫霾尽","count":4054878.4000000004},{"url":"/weibo?q=%E8%94%A1%E5%8D%93%E5%AE%9C%20%E7%A6%BB%E5%A9%9A%E4%BA%86%E5%B0%B1%E4%B8%8D%E8%83%BD%E4%BB%8E%E5%A4%B4%E5%BC%80%E5%A7%8B%E5%90%97&Refer=top","text":"蔡卓宜 离婚了就不能从头开始吗","count":4041080},{"url":"/weibo?q=%23%E9%BB%84%E5%A5%95%E7%BA%A6%E4%BC%9A%E5%AF%B9%E8%B1%A1%E6%98%AF%E9%99%86%E5%BE%8B%E5%B8%88%23&Refer=top","text":"黄奕约会对象是陆律师","count":3885405.5999999996},{"url":"/weibo?q=%23%E5%B1%B1%E4%B8%9C%E9%87%91%E7%9F%BF%E7%88%86%E7%82%B8%E4%BA%8B%E6%95%85%E4%B8%80%E7%9F%BF%E5%B7%A5%E6%88%90%E5%8A%9F%E5%8D%87%E4%BA%95%23&Refer=top","text":"山东金矿爆炸事故一矿工成功升井","count":3120269},{"url":"/weibo?q=%23%E6%92%92%E8%B4%9D%E5%AE%81%E7%AA%81%E7%84%B6%E8%B7%9F%E7%BD%91%E5%8F%8B%E5%AF%B9%E8%AF%9D%E6%8A%8A%E8%96%87%E5%A8%85%E7%9C%8B%E6%84%A3%E4%BA%86%23&Refer=top","text":"撒贝宁突然跟网友对话把薇娅看愣了","count":2876883.2},{"url":"/weibo?q=%23%E6%9D%9C%E6%B7%B3%E9%A1%B6%E8%83%AF%23&Refer=top","text":"杜淳顶胯","count":2773954.8},{"url":"/weibo?q=%E5%90%88%E6%88%90%E5%A4%A7%E8%A5%BF%E7%93%9C&Refer=top","text":"合成大西瓜","count":2261866.8},{"url":"/weibo?q=%23%E8%B7%AA%E4%B8%8B%E7%9A%84%E8%AD%A6%E5%AF%9F%23&Refer=top","text":"跪下的警察","count":2124497},{"url":"/weibo?q=%23%E5%8D%97%E4%BA%AC%E7%A0%B4%E8%8E%B719%E5%B9%B4%E5%89%8D%E6%8A%A2%E5%8A%AB%E6%9D%80%E4%BA%BA%E6%A1%88%23&Refer=top","text":"南京破获19年前抢劫杀人案","count":2036671.2},{"url":"/weibo?q=%E9%9D%92%E4%BD%A03%E8%AE%AD%E7%BB%83%E7%94%9F%E5%AE%98%E5%AE%A3&Refer=top","text":"青你3训练生官宣","count":2026281.5999999999},{"url":"/weibo?q=%23%E5%90%B4%E4%B8%96%E5%8B%8B%E7%9C%8B%E4%B8%89%E5%8D%81%E8%80%8C%E5%B7%B2%E5%93%AD%E4%BA%86%23&Refer=top","text":"吴世勋看三十而已哭了","count":1923264.8},{"url":"/weibo?q=%23%E5%8C%97%E4%BA%AC%E6%9C%89%E5%8C%BB%E9%99%A2%E6%8B%92%E8%AF%8A%E4%B8%AD%E9%AB%98%E9%A3%8E%E9%99%A9%E5%9C%B0%E5%8C%BA%E6%82%A3%E8%80%85%E8%A2%AB%E7%BA%A6%E8%B0%88%23&Refer=top","text":"北京有医院拒诊中高风险地区患者被约谈","count":1917764.4},{"url":"/weibo?q=%23%E6%B1%9F%E8%8B%8F%E9%95%87%E6%B1%9F%E7%A1%AE%E8%AF%8A%E7%97%85%E4%BE%8B%E7%88%B6%E4%BA%B2%E6%A0%B8%E9%85%B8%E9%98%B3%E6%80%A7%23&Refer=top","text":"江苏镇江确诊病例父亲核酸阳性","count":1764685},{"url":"/weibo?q=%23%E5%BE%AE%E4%BF%A1%E7%8A%B6%E6%80%81%E8%BF%98%E5%8F%AF%E4%BB%A5%E8%BF%99%E6%A0%B7%E7%8E%A9%23&Refer=top","text":"微信状态还可以这样玩","count":1761530.4},{"url":"/weibo?q=%2330%E4%BA%BA%E8%B4%A9%E5%8D%966%E4%BA%BF%E6%9D%A1%E4%B8%AA%E4%BA%BA%E4%BF%A1%E6%81%AF%E8%8E%B7%E5%88%A9800%E4%BD%99%E4%B8%87%23&Refer=top","text":"30人贩卖6亿条个人信息获利800余万","count":1611367.2},{"url":"/weibo?q=%23%E6%BB%B4%E6%BB%B4%E5%9B%9E%E5%BA%94%E9%95%BF%E6%B2%99%E5%A5%B3%E7%94%9F%E4%B9%98%E7%BD%91%E7%BA%A6%E8%BD%A6%E5%90%8E%E5%A4%B1%E8%81%94%23&Refer=top","text":"滴滴回应长沙女生乘网约车后失联","count":1440998.4},{"url":"/weibo?q=%23%E6%9D%AD%E5%B7%9E%E4%B8%80%E4%BC%81%E4%B8%9A%E5%91%98%E5%B7%A5%E5%87%BA%E5%A2%83%E5%90%8E%E4%B8%89%E5%A4%A9%E6%A0%B8%E9%85%B8%E6%A3%80%E6%B5%8B%E9%98%B3%E6%80%A7%23&Refer=top","text":"杭州一企业员工出境后三天核酸检测阳性","count":1367252},{"url":"/weibo?q=%E9%80%9A%E5%8C%96%E7%89%A9%E8%B5%84&Refer=top","text":"通化物资","count":1322391},{"url":"/weibo?q=%23%E9%80%9A%E5%8C%96%E5%B7%B2%E6%9C%89800%E5%A4%9A%E5%90%8D%E5%BF%97%E6%84%BF%E8%80%85%E5%85%A8%E5%8A%9B%E9%85%8D%E9%80%81%E7%89%A9%E8%B5%84%23&Refer=top","text":"通化已有800多名志愿者全力配送物资","count":1317102},{"url":"/weibo?q=%E5%B1%B1%E4%B8%9C%E9%87%91%E7%9F%BF%E7%88%86%E7%82%B8%E4%BA%8B%E6%95%85&Refer=top","text":"山东金矿爆炸事故","count":1311952},{"url":"/weibo?q=%23%E5%90%89%E6%9E%97%E9%80%9A%E5%8C%96%E5%B0%B1%E7%94%9F%E6%B4%BB%E7%89%A9%E8%B5%84%E9%85%8D%E9%80%81%E4%B8%8D%E5%8F%8A%E6%97%B6%E9%97%AE%E9%A2%98%E8%87%B4%E6%AD%89%23&Refer=top","text":"吉林通化就生活物资配送不及时问题致歉","count":1264817},{"url":"/weibo?q=%E7%BD%97%E7%BF%94%E4%BA%8E%E8%B0%A6%20%E6%B3%95%E5%BE%8B%E7%9B%B8%E5%A3%B0&Refer=top","text":"罗翔于谦 法律相声","count":1261063.2},{"url":"/weibo?q=%23%E5%B1%B1%E4%B8%9C%E9%87%91%E7%9F%BF%E7%88%86%E7%82%B8%E4%BA%8B%E6%95%85%E5%8F%883%E4%BD%8D%E7%9F%BF%E5%B7%A5%E5%8D%87%E4%BA%95%23&Refer=top","text":"山东金矿爆炸事故又3位矿工升井","count":1255666},{"url":"/weibo?q=%23%E5%A4%AB%E8%B5%96%E7%93%9C%E5%A6%B9%E5%88%86%E6%89%8B%23&Refer=top","text":"夫赖瓜妹分手","count":1239604},{"url":"/weibo?q=%23%E6%B5%99%E6%B1%9F%E6%96%B0%E6%98%8C%E5%8F%91%E7%8E%B01%E4%BE%8B%E6%A0%B8%E9%85%B8%E7%BB%93%E6%9E%9C%E5%8F%AF%E7%96%91%E4%BA%BA%E5%91%98%23&Refer=top","text":"浙江新昌发现1例核酸结果可疑人员","count":1236756},{"url":"/weibo?q=%E8%89%BE%E5%85%8B%E9%87%8C%E9%87%8C&Refer=top","text":"艾克里里","count":1231381},{"url":"/weibo?q=%23%E8%AD%A6%E6%96%B9%E9%80%9A%E6%8A%A522%E5%B2%81%E5%A5%B3%E7%94%9F%E4%B9%98%E7%BD%91%E7%BA%A6%E8%BD%A6%E5%90%8E%E5%A4%B1%E8%81%94%23&Refer=top","text":"警方通报22岁女生乘网约车后失联","count":1224230},{"url":"/weibo?q=%E7%94%B7%E5%AD%90%E9%A9%BE%E6%97%A0%E7%89%8C%E6%96%B0%E8%BD%A6%E6%92%9E%E8%A1%8C%E4%BA%BA%E8%87%B44%E6%AD%BB6%E4%BC%A4&Refer=top","text":"男子驾无牌新车撞行人致4死6伤","count":1209408},{"url":"/weibo?q=%23%E4%BA%BA%E6%B0%91%E6%97%A5%E6%8A%A5%E8%AF%84%E6%95%A6%E7%85%8C%E9%98%B2%E6%8A%A4%E6%9E%97%E8%A2%AB%E6%AF%81%23&Refer=top","text":"人民日报评敦煌防护林被毁","count":1200063.5999999999},{"url":"/weibo?q=%23%E9%81%9B%E7%8B%97%E6%8B%B4%E7%BB%B3%E5%85%A5%E6%B3%95%23&Refer=top","text":"遛狗拴绳入法","count":1198857.5999999999},{"url":"/weibo?q=%23%E4%B8%8A%E6%B5%B7%E4%BA%BA%E5%9D%87%E7%94%9F%E4%BA%A7%E6%80%BB%E5%80%BC%E7%AA%81%E7%A0%B42.3%E4%B8%87%E7%BE%8E%E5%85%83%23&Refer=top","text":"上海人均生产总值突破2.3万美元","count":1180935},{"url":"/weibo?q=%23%E6%96%B0%E5%86%A0%E7%97%85%E6%AF%92%E7%96%AB%E8%8B%97%E9%9C%80%E8%A6%81%E6%AF%8F%E5%B9%B4%E6%8E%A5%E7%A7%8D%E5%90%97%23&Refer=top","text":"新冠病毒疫苗需要每年接种吗","count":1178804.4},{"url":"/weibo?q=%23%E7%BE%8E%E5%9B%BD%E7%BD%91%E8%B4%AD%E9%80%80%E8%B4%A7%E9%87%8F%E9%A3%99%E5%8D%87%23&Refer=top","text":"美国网购退货量飙升","count":1145355},{"url":"/weibo?q=%23%E5%88%9B4%E5%88%B6%E6%9C%8D%23&Refer=top","text":"创4制服","count":1138706},{"url":"/weibo?q=%E9%95%87%E6%B1%9F&Refer=top","text":"镇江","count":1115378.4},{"url":"/weibo?q=%23%E7%AB%96%E5%B1%8F%E8%A7%86%E9%A2%91%E8%83%BD%E5%8F%96%E4%BB%A3%E6%A8%AA%E5%B1%8F%E5%90%97%23&Refer=top","text":"竖屏视频能取代横屏吗","count":1070053.2},{"url":"/weibo?q=%23%E9%80%9A%E5%8C%96%E6%96%B0%E5%A2%9E%E7%A1%AE%E8%AF%8A2%E4%BE%8B%23&Refer=top","text":"通化新增确诊2例","count":1044032.3999999999},{"url":"/weibo?q=%23%E9%99%88%E9%92%B0%E7%90%AA%E6%9E%97%E4%B8%80%E5%90%BB%E6%88%8F%23&Refer=top","text":"陈钰琪林一吻戏","count":1028843},{"url":"/weibo?q=%23%E5%BC%A0%E6%AA%AC%E5%8F%91%E9%95%BF%E6%96%87%E5%91%8A%E5%88%AB%E6%88%91%E5%B0%B1%E6%98%AF%E6%BC%94%E5%91%98%23&Refer=top","text":"张檬发长文告别我就是演员","count":1024268.3999999999},{"url":"/weibo?q=%E7%8E%84%E5%BD%AC%E5%8F%91%E8%A1%A8%E8%8E%B7%E5%A5%96%E6%84%9F%E8%A8%80%E6%97%B6%E6%84%9F%E8%B0%A2%E5%AD%99%E8%89%BA%E7%8F%8D&Refer=top","text":"玄彬发表获奖感言时感谢孙艺珍","count":1016584.7999999999},{"url":"/weibo?q=%23%E6%B7%B1%E5%9C%B3%E5%8F%91%E7%8E%B01%E4%BE%8B%E6%96%B0%E5%86%A0%E8%82%BA%E7%82%8E%E9%98%B3%E6%80%A7%23&Refer=top","text":"深圳发现1例新冠肺炎阳性","count":979014},{"url":"/weibo?q=%23%E9%A9%BE%E8%BD%A6%E6%97%B6%E5%8D%83%E4%B8%87%E5%88%AB%E9%9A%8F%E4%BE%BF%E6%91%B8%E8%84%B8%23&Refer=top","text":"驾车时千万别随便摸脸","count":959808},{"url":"/weibo?q=%23%E7%89%B9%E6%9C%97%E6%99%AE%E7%A6%BB%E4%BB%BB%E5%90%8E%E9%A6%96%E6%AC%A1%E5%8F%91%E5%A3%B0%23&Refer=top","text":"特朗普离任后首次发声","count":937744.7999999999}]