[{"url":"/weibo?q=%23%E7%9B%96%E8%8C%A8%E6%89%BF%E8%AE%A4%E6%9B%BE%E4%B8%8E%E5%A5%B3%E5%91%98%E5%B7%A5%E5%A9%9A%E5%A4%96%E6%83%85%23&Refer=top","text":"盖茨承认曾与女员工婚外情","count":2949382.4000000004},{"url":"/weibo?q=%23A%E5%A6%B9%E5%AE%A3%E5%B8%83%E7%BB%93%E5%A9%9A%23&Refer=top","text":"A妹宣布结婚","count":2683947.2},{"url":"/weibo?q=%23%E5%A7%9C%E6%BD%AE%E6%96%B9%E5%9B%9E%E5%BA%94%E9%BA%A6%E8%BF%AA%E5%A8%9C%E6%80%80%E4%BA%8C%E8%83%8E%23&Refer=top","text":"姜潮方回应麦迪娜怀二胎","count":2092388.8},{"url":"/weibo?q=%23%E6%99%AF%E7%94%9C%E9%97%AE%E5%88%98%E5%AE%87%E5%AE%81%E7%9B%B4%E6%92%AD%E5%92%8B%E6%B2%A1%E5%8F%AB%E5%A5%B9%23&Refer=top","text":"景甜问刘宇宁直播咋没叫她","count":1636965.5999999999},{"url":"/weibo?q=%23%E6%B5%99%E6%B1%9F%E4%B8%80%E7%89%B9%E6%96%AF%E6%8B%89%E6%92%9E%E5%80%92%E4%B8%A4%E4%BA%A4%E8%AD%A6%23&Refer=top","text":"浙江一特斯拉撞倒两交警","count":1612782},{"url":"/weibo?q=%23%E9%92%9F%E5%8D%97%E5%B1%B1%E8%AF%B4%E4%B8%AD%E5%9B%BD%E9%9C%80%E5%B0%BD%E5%BF%AB%E5%BB%BA%E7%AB%8B%E7%BE%A4%E4%BD%93%E5%85%8D%E7%96%AB%23&Refer=top","text":"钟南山说中国需尽快建立群体免疫","count":1526824.8},{"url":"/weibo?q=%E5%88%98%E5%AE%87%E5%AE%81%20%E6%88%91%E9%83%BD%E5%B8%8C%E6%9C%9B%E8%90%A5%E9%94%80%E5%8F%B7%E8%AF%B4%E7%9A%84%E6%98%AF%E7%9C%9F%E7%9A%84&Refer=top","text":"刘宇宁 我都希望营销号说的是真的","count":1223582.4000000001},{"url":"/weibo?q=%23Marco%E6%89%BF%E8%AE%A4%E4%B8%8E%E6%9D%8E%E6%85%A7%E5%BD%AC%E6%81%8B%E6%83%85%23&Refer=top","text":"Marco承认与李慧彬恋情","count":1160927.2},{"url":"/weibo?q=%23%E7%BE%8E%E5%9B%BD%E5%90%91%E4%BB%A5%E8%89%B2%E5%88%97%E5%87%BA%E5%94%AE7.35%E4%BA%BF%E7%BE%8E%E5%85%83%E6%AD%A6%E5%99%A8%23&Refer=top","text":"美国向以色列出售7.35亿美元武器","count":1137966},{"url":"/weibo?q=%E9%9A%BE%E5%90%AC&Refer=top","text":"难听","count":1125015.5999999999},{"url":"/weibo?q=%23%E6%AC%A2%E7%91%9E%E8%A2%AB%E5%88%A4%E6%94%AF%E4%BB%98%E9%9D%92%E4%BA%91%E5%BF%97%E6%AC%A0%E6%AC%BE600%E4%B8%87%23&Refer=top","text":"欢瑞被判支付青云志欠款600万","count":1117634.4000000001},{"url":"/weibo?q=%23%E6%88%90%E9%83%BD10%E5%B2%81%E5%A5%B3%E5%AD%A9%E5%86%8D%E7%A0%B4%E5%90%89%E5%B0%BC%E6%96%AF%E7%BA%AA%E5%BD%95%23&Refer=top","text":"成都10岁女孩再破吉尼斯纪录","count":1114687.2},{"url":"/weibo?q=%23%E5%88%98%E5%AE%87%E5%AE%81%E5%8F%AB%E9%94%99%E5%BE%90%E5%BC%80%E9%AA%8B%E5%90%8D%E5%AD%97%23&Refer=top","text":"刘宇宁叫错徐开骋名字","count":1109929.2},{"url":"/weibo?q=%23%E7%8E%8B%E5%AD%90%E5%A5%87%E8%8B%8F%E6%99%93%E5%BD%A4%E5%9C%A8%E5%BF%99%E7%9D%80%E5%86%99%E8%AE%BA%E6%96%87%23&Refer=top","text":"王子奇苏晓彤在忙着写论文","count":1097385.5999999999},{"url":"/weibo?q=%23%E5%85%AD%E5%AE%89%E7%99%BE%E4%B8%87%E4%BA%BA%E5%8F%A3%E6%A0%B8%E9%85%B8%E6%A3%80%E6%B5%8B%E7%BB%93%E6%9E%9C%E5%87%BA%E6%9D%A5%E4%BA%86%23&Refer=top","text":"六安百万人口核酸检测结果出来了","count":1084646.4},{"url":"/weibo?q=%23%E5%A4%A7%E5%A4%B4%E5%84%BF%E5%AD%90%E7%9A%84%E7%9C%9F%E5%90%8D%E5%8F%AB%E5%A4%B4%E5%A4%AA%E5%85%83%23&Refer=top","text":"大头儿子的真名叫头太元","count":1079972.4},{"url":"/weibo?q=%23%E7%94%9F%E7%8C%AA%E4%BB%B7%E6%A0%BC%E8%B7%8C%E7%A0%B4%E4%B8%80%E6%96%A410%E5%85%83%23&Refer=top","text":"生猪价格跌破一斤10元","count":1071181.2},{"url":"/weibo?q=%23%E6%AE%B7%E4%B8%96%E8%88%AA%E5%BF%AB%E6%89%8B%E8%B4%A6%E5%8F%B7%E8%A2%AB%E5%B0%81%E7%A6%81%23&Refer=top","text":"殷世航快手账号被封禁","count":1058923.2},{"url":"/weibo?q=%23%E5%B9%BF%E8%A5%BF%E5%8C%97%E6%B5%B7%E7%BA%A2%E6%A0%91%E6%9E%97%E5%A4%A7%E7%89%87%E6%B6%88%E5%A4%B1%23&Refer=top","text":"广西北海红树林大片消失","count":1029615.6},{"url":"/weibo?q=%E5%BE%A1%E8%B5%90%E5%B0%8F%E4%BB%B5%E4%BD%9C&Refer=top","text":"御赐小仵作","count":1019662.7999999999},{"url":"/weibo?q=%E4%B9%8C%E9%B8%A6%E5%B0%8F%E5%A7%90%E4%B8%8E%E8%9C%A5%E8%9C%B4%E5%85%88%E7%94%9F&Refer=top","text":"乌鸦小姐与蜥蜴先生","count":1005504},{"url":"/weibo?q=%23%E7%A7%A6%E6%B5%B7%E7%92%90%20%E6%88%91%E6%8B%8D%E7%9A%84%E8%80%81%E5%85%AC%E5%92%8C%E8%80%81%E5%85%AC%E6%8B%8D%E7%9A%84%E6%88%91%23&Refer=top","text":"秦海璐 我拍的老公和老公拍的我","count":994094.3999999999},{"url":"/weibo?q=%23Amber%E7%82%B9%E7%9A%84%E8%82%89%E5%A4%B9%E9%A6%8D%23&Refer=top","text":"Amber点的肉夹馍","count":983274},{"url":"/weibo?q=%23%E5%85%AD%E5%AE%892%E4%BE%8B%E6%97%A0%E7%97%87%E7%8A%B6%E6%84%9F%E6%9F%93%E8%80%85%E8%AF%A6%E6%83%85%23&Refer=top","text":"六安2例无症状感染者详情","count":982549.6000000001},{"url":"/weibo?q=%23%E5%8D%B0%E5%BA%A6%E6%81%92%E6%B2%B3%E7%8E%B0%E6%B5%AE%E5%B0%B8%E5%8E%9F%E5%9B%A0%23&Refer=top","text":"印度恒河现浮尸原因","count":965400},{"url":"/weibo?q=%23%E5%BD%93%E5%A6%88%E5%A6%88%E8%AF%B4%E7%BB%99%E4%BD%A0%E6%89%93%E5%85%AD%E4%B8%87%E7%94%9F%E6%B4%BB%E8%B4%B9%23&Refer=top","text":"当妈妈说给你打六万生活费","count":906710.4},{"url":"/weibo?q=%23%E5%BA%B7%E8%BE%89%E8%AF%B4%E7%96%AB%E8%8B%97%E6%8E%A5%E7%A7%8D%E9%80%9F%E5%BA%A6%E8%BF%98%E5%BE%97%E5%8A%A0%E5%BF%AB%23&Refer=top","text":"康辉说疫苗接种速度还得加快","count":828772},{"url":"/weibo?q=%23%E6%BD%9C%E5%9C%A8%E5%AE%B6%E6%9A%B4%E8%80%85%E7%9A%8413%E4%B8%AA%E7%89%B9%E5%BE%81%23&Refer=top","text":"潜在家暴者的13个特征","count":780738},{"url":"/weibo?q=%23%E6%AF%8F%E5%91%A8%E5%B7%A5%E4%BD%9C%E8%B6%8555%E5%B0%8F%E6%97%B6%E6%88%96%E5%BF%83%E8%84%8F%E7%97%85%E8%87%B4%E6%AD%BB%23&Refer=top","text":"每周工作超55小时或心脏病致死","count":779560},{"url":"/weibo?q=%23%E7%94%B5%E6%B1%A0%E5%8E%9F%E6%9D%90%E6%96%99%E4%BB%B7%E6%A0%BC%E4%B8%8A%E6%B6%A8%23&Refer=top","text":"电池原材料价格上涨","count":760621.2},{"url":"/weibo?q=%23%E6%BC%94%E4%BA%86%E4%B8%A4%E5%88%86%E9%92%9F%E4%BD%A0%E4%B9%9F%E4%BF%A1%23&Refer=top","text":"演了两分钟你也信","count":741192},{"url":"/weibo?q=%23%E6%80%A7%E8%BD%AC%E5%90%8E%E7%9A%84INTO1%23&Refer=top","text":"性转后的INTO1","count":735412.7999999999},{"url":"/weibo?q=%23%E8%BE%BD%E5%AE%81%E6%96%B0%E5%A2%9E4%E4%BE%8B%E6%9C%AC%E5%9C%9F%E7%A1%AE%E8%AF%8A%23&Refer=top","text":"辽宁新增4例本土确诊","count":631518.4},{"url":"/weibo?q=%E8%B0%A2%E5%A8%9C&Refer=top","text":"谢娜","count":572643.6},{"url":"/weibo?q=%23%E6%96%B0%E4%B8%9C%E6%96%B9%E5%AD%A6%E8%80%8C%E6%80%9D%E7%AD%89%E8%A2%AB%E5%8C%97%E4%BA%AC%E5%B8%82%E6%95%99%E5%A7%94%E7%82%B9%E5%90%8D%23&Refer=top","text":"新东方学而思等被北京市教委点名","count":572116},{"url":"/weibo?q=%23%E6%8B%9C%E7%99%BB%E5%85%AC%E5%BC%80%E5%91%BC%E5%90%81%E5%B7%B4%E4%BB%A5%E5%81%9C%E7%81%AB%23&Refer=top","text":"拜登公开呼吁巴以停火","count":557200},{"url":"/weibo?q=%23%E5%BE%90%E5%BC%80%E9%AA%8B%E5%9B%9E%E5%BA%94%E5%90%8D%E5%AD%97%E8%A2%AB%E5%8F%AB%E9%94%99%23&Refer=top","text":"徐开骋回应名字被叫错","count":534282.4},{"url":"/weibo?q=%E9%81%87%E9%BE%99&Refer=top","text":"遇龙","count":528738.4},{"url":"/weibo?q=%23%E5%8D%B0%E5%BA%A6%E6%9C%89%E4%BA%BA%E6%8B%BF%E7%81%AD%E7%81%AB%E5%99%A8%E5%BD%93%E6%B0%A7%E6%B0%94%E7%93%B6%E5%8D%96%23&Refer=top","text":"印度有人拿灭火器当氧气瓶卖","count":528124},{"url":"/weibo?q=%23%E4%BD%95%E5%BE%B7%E7%91%9E%E9%81%93%E6%AD%89%23&Refer=top","text":"何德瑞道歉","count":522930.4},{"url":"/weibo?q=%23%E4%BC%AF%E8%BF%9C%E5%BD%93%E8%BF%87%E6%9D%8E%E4%BD%B3%E7%90%A6%E7%9A%84%E8%88%9E%E8%B9%88%E8%80%81%E5%B8%88%23&Refer=top","text":"伯远当过李佳琦的舞蹈老师","count":516404},{"url":"/weibo?q=%23%E7%8E%8B%E4%B8%80%E5%8D%9A28%E5%B2%81%E7%9A%84%E4%BD%A0%E4%B8%BB%E9%A2%98%E6%9B%B2%23&Refer=top","text":"王一博28岁的你主题曲","count":514496.80000000005},{"url":"/weibo?q=%23%E7%8B%97%E7%8B%97%E8%A6%81%E6%98%AF%E9%95%BF%E4%B8%8D%E5%A4%A7%E8%AF%A5%E5%A4%9A%E5%A5%BD%23&Refer=top","text":"狗狗要是长不大该多好","count":512652},{"url":"/weibo?q=%23%E6%B4%BE%E5%87%BA%E6%89%80%E5%9B%9E%E5%BA%94%E8%80%81%E4%BA%BA%E4%B9%98%E5%87%BA%E7%A7%9F%E8%BD%A6%E7%94%A8%E7%9A%AE%E5%B8%A6%E5%8B%92%E5%8F%B8%E6%9C%BA%23&Refer=top","text":"派出所回应老人乘出租车用皮带勒司机","count":512178},{"url":"/weibo?q=%23%E5%B7%B4%E5%8B%92%E6%96%AF%E5%9D%A6%E5%B9%B8%E5%AD%98%E5%84%BF%E7%AB%A5%E5%8F%97%E4%B8%A5%E9%87%8D%E5%BF%83%E7%90%86%E5%88%9B%E4%BC%A4%23&Refer=top","text":"巴勒斯坦幸存儿童受严重心理创伤","count":500805.60000000003},{"url":"/weibo?q=%23%E6%B2%88%E9%98%B3%E6%96%B0%E5%A2%9E2%E4%BE%8B%E7%A1%AE%E8%AF%8A%E7%97%85%E4%BE%8B%E8%BD%A8%E8%BF%B9%E5%85%AC%E5%B8%83%23&Refer=top","text":"沈阳新增2例确诊病例轨迹公布","count":500763.2},{"url":"/weibo?q=%23%E8%BF%99%E7%BE%A4%E7%BE%8A%E5%BE%97%E7%BB%83%E4%BA%86%E5%A4%9A%E5%B0%91%E6%B7%B1%E8%B9%B2%23&Refer=top","text":"这群羊得练了多少深蹲","count":499808.80000000005},{"url":"/weibo?q=%23%E5%A4%A7%E7%88%B7%E5%85%8D%E8%B4%B9%E6%97%85%E6%B8%B8%E8%A2%AB%E5%BF%BD%E6%82%A0%E4%B9%B0%E4%BA%862%E4%B8%87%E5%85%83%E6%8A%97%E7%99%8C%E8%8D%AF%23&Refer=top","text":"大爷免费旅游被忽悠买了2万元抗癌药","count":493417.60000000003},{"url":"/weibo?q=%23%E5%AD%99%E6%9D%A8%E6%A1%88%E9%87%8D%E5%AE%A1%E5%90%AC%E8%AF%81%E4%BC%9A%E4%B8%8D%E5%85%AC%E5%BC%80%E4%B8%BE%E8%A1%8C%23&Refer=top","text":"孙杨案重审听证会不公开举行","count":492912.80000000005},{"url":"/weibo?q=%23%E8%91%A3%E5%AD%90%E5%81%A5%E8%87%AA%E5%88%B6%E5%8E%8B%E7%BC%A9%E7%B1%B3%E9%A5%AD%23&Refer=top","text":"董子健自制压缩米饭","count":459379.2}]