[{"url":"/weibo?q=%23%E4%B8%AD%E5%9B%BD%E5%A5%B3%E6%8E%92VS%E7%BE%8E%E5%9B%BD%E5%A5%B3%E6%8E%92%23&Refer=top","text":"中国女排VS美国女排","count":26563287.599999998},{"url":"/weibo?q=%23%E9%A9%AC%E9%BE%99%E6%A8%8A%E6%8C%AF%E4%B8%9C%E5%87%BA%E6%88%98%E4%B9%92%E4%B9%93%E7%90%83%E7%94%B7%E5%8D%95%23&Refer=top","text":"马龙樊振东出战乒乓球男单","count":16971349.2},{"url":"/weibo?q=%23%E5%BC%A0%E5%AE%B6%E9%BD%90%E9%99%88%E8%8A%8B%E6%B1%90%E5%A5%B3%E5%AD%90%E5%8F%8C%E4%BA%BA%E5%8D%81%E7%B1%B3%E5%8F%B0%E5%A4%BA%E9%87%91%23&Refer=top","text":"张家齐陈芋汐女子双人十米台夺金","count":16194992},{"url":"/weibo?q=%23%E8%8A%A6%E7%8E%89%E8%8F%B2%E6%8E%89%E6%9D%A0%23&Refer=top","text":"芦玉菲掉杠","count":14083522.799999999},{"url":"/weibo?q=%23%E6%9D%A8%E5%80%A9%E6%9D%A8%E7%9A%93%E7%84%B6%E6%B0%94%E6%AD%A5%E6%9E%AA%E6%B7%B7%E5%90%88%E5%9B%A2%E4%BD%93%E5%A4%BA%E9%87%91%23&Refer=top","text":"杨倩杨皓然气步枪混合团体夺金","count":13236289},{"url":"/weibo?q=%23%E5%BA%9E%E4%BC%9F%E5%A7%9C%E5%86%89%E9%A6%A8%E6%B0%94%E6%89%8B%E6%9E%AA%E6%B7%B7%E5%90%88%E5%9B%A2%E4%BD%93%E5%A4%BA%E9%87%91%23&Refer=top","text":"庞伟姜冉馨气手枪混合团体夺金","count":12279732},{"url":"/weibo?q=%23%E6%9D%A8%E5%80%A9%E7%BB%99%E7%99%BD%E6%95%AC%E4%BA%AD%E5%8F%91%E8%AF%AD%E9%9F%B3%23&Refer=top","text":"杨倩给白敬亭发语音","count":8696721.6},{"url":"/weibo?q=%23%E5%BE%AE%E4%BF%A1%E6%9A%82%E5%81%9C%E4%B8%AA%E4%BA%BA%E5%B8%90%E5%8F%B7%E6%96%B0%E7%94%A8%E6%88%B7%E6%B3%A8%E5%86%8C%23&Refer=top","text":"微信暂停个人帐号新用户注册","count":7764471.6},{"url":"/weibo?q=%23%E8%AE%B8%E6%98%95%E5%88%98%E8%AF%97%E9%9B%AF%E8%8E%B7%E6%B7%B7%E5%8F%8C%E9%93%B6%E7%89%8C%23&Refer=top","text":"许昕刘诗雯获混双银牌","count":7428048},{"url":"/weibo?q=%23%E9%83%8E%E5%B9%B3%E8%A1%A8%E7%A4%BA%E6%9C%B1%E5%A9%B7%E5%B7%B2%E7%BB%8F%E5%B0%BD%E5%8A%9B%E4%BA%86%23&Refer=top","text":"郎平表示朱婷已经尽力了","count":7190905.2},{"url":"/weibo?q=%23%E4%B8%AD%E5%9B%BD%E7%AC%AC%E4%B8%80%E6%B3%A2%E9%87%91%E7%89%8C%E4%B9%9D%E5%AE%AB%E6%A0%BC%23&Refer=top","text":"中国第一波金牌九宫格","count":7122915.6},{"url":"/weibo?q=%E6%9C%B1%E5%A9%B7%E5%BC%A0%E5%B8%B8%E5%AE%81%20%E5%8E%89%E5%AE%B3&Refer=top","text":"朱婷张常宁 厉害","count":6870202.8},{"url":"/weibo?q=%23%E8%B7%B3%E6%B0%B4%E5%A5%B3%E5%AD%90%E5%8F%8C%E4%BA%BA10%E7%B1%B3%E8%B7%B3%E5%8F%B0%E5%86%B3%E8%B5%9B%23&Refer=top","text":"跳水女子双人10米跳台决赛","count":6742986},{"url":"/weibo?q=%E9%A9%AC%E9%BE%99%20%E4%B8%8D%E8%83%BD%E5%90%B9%E7%90%83%E5%B0%B1%E5%90%B9%E6%89%8B&Refer=top","text":"马龙 不能吹球就吹手","count":6130426.8},{"url":"/weibo?q=%23%E6%9D%A8%E5%80%A9%E5%A6%88%E5%A6%88%E8%AF%B4%E6%B2%B9%E7%84%96%E5%A4%A7%E8%99%BE%E7%AE%A1%E5%A4%9F%23&Refer=top","text":"杨倩妈妈说油焖大虾管够","count":6066666},{"url":"/weibo?q=%23%E6%9C%B1%E5%A9%B7%E6%89%8B%E8%85%95%E7%96%BC%E5%BE%97%E5%8F%91%E4%B8%8D%E4%B8%8A%E5%8A%9B%23&Refer=top","text":"朱婷手腕疼得发不上力","count":5870636},{"url":"/weibo?q=%23%E6%9D%A8%E8%88%92%E4%BA%883%E5%88%86%23&Refer=top","text":"杨舒予3分","count":5689251.6},{"url":"/weibo?q=%E6%97%A5%E6%9C%AC%E8%B7%B3%E6%B0%B4%E5%A4%B1%E8%AF%AF&Refer=top","text":"日本跳水失误","count":5566610},{"url":"/weibo?q=%23%E4%B8%AD%E5%9B%BD%E4%BD%93%E6%93%8D%E5%A5%B3%E5%9B%A2%E7%AC%AC%E4%B8%83%E5%90%8D%23&Refer=top","text":"中国体操女团第七名","count":5208834},{"url":"/weibo?q=%23%E5%A4%A7%E5%9D%82%E7%9B%B4%E7%BE%8E%E8%A2%AB%E6%B7%98%E6%B1%B0%23&Refer=top","text":"大坂直美被淘汰","count":5154889.2},{"url":"/weibo?q=%23%E6%B2%B3%E5%8D%97%E6%9A%B4%E9%9B%A8%E5%90%8E%E5%8F%88%E5%B0%86%E8%BF%8E%E6%88%98%E5%8F%B0%E9%A3%8E%E7%83%9F%E8%8A%B1%23&Refer=top","text":"河南暴雨后又将迎战台风烟花","count":5106879.6},{"url":"/weibo?q=%23%E8%AE%B8%E6%98%95%E8%AF%B4%E6%B2%A1%E7%BB%99%E8%87%AA%E5%B7%B1%E4%B8%80%E4%B8%AA%E5%A5%BD%E7%9A%84%E7%BB%93%E5%B1%80%23&Refer=top","text":"许昕说没给自己一个好的结局","count":5100413.600000001},{"url":"/weibo?q=%23%E5%AD%99%E4%B8%80%E6%96%87%E5%8F%97%E4%BC%A4%23&Refer=top","text":"孙一文受伤","count":4863042},{"url":"/weibo?q=%23%E5%BE%AE%E4%BF%A1%E7%BB%88%E4%BA%8E%E6%94%AF%E6%8C%81%E5%A4%9A%E8%AE%BE%E5%A4%87%E5%90%8C%E6%97%B6%E5%9C%A8%E7%BA%BF%23&Refer=top","text":"微信终于支持多设备同时在线","count":4829716.8},{"url":"/weibo?q=%23%E5%87%BB%E5%89%91%E6%95%99%E7%BB%83%E8%B5%9B%E5%90%8E%E5%90%91%E5%A5%B3%E5%BE%92%E5%BC%9F%E6%B1%82%E5%A9%9A%E6%88%90%E5%8A%9F%23&Refer=top","text":"击剑教练赛后向女徒弟求婚成功","count":4704914.399999999},{"url":"/weibo?q=%E4%B8%AD%E5%9B%BD%E5%A5%B3%E6%8E%92%E7%AC%AC%E4%B8%80%E5%B1%80%E6%9A%82%E6%97%B6%E8%90%BD%E5%90%8E&Refer=top","text":"中国女排第一局暂时落后","count":4699623.6},{"url":"/weibo?q=%23%E9%87%91%E9%9D%96%E8%88%92%E5%A5%95%E6%A9%99%E6%81%8B%E6%83%85%23&Refer=top","text":"金靖舒奕橙恋情","count":4583896},{"url":"/weibo?q=%E4%BF%84%E7%BD%97%E6%96%AF%E5%B9%B3%E8%A1%A1%E6%9C%A8%E5%A4%B1%E8%AF%AF&Refer=top","text":"俄罗斯平衡木失误","count":4496960.399999999},{"url":"/weibo?q=%23%E4%B8%8B%E9%A5%BA%E5%AD%90%E7%9A%84%E6%B0%B4%E8%8A%B1%E9%83%BD%E6%AF%94%E8%BF%99%E5%A4%A7%23&Refer=top","text":"下饺子的水花都比这大","count":4253888},{"url":"/weibo?q=%23%E6%97%A5%E6%9C%AC%E4%B9%92%E4%B9%93%E7%94%B7%E5%8D%95%E9%80%89%E6%89%8B%E5%85%A8%E9%83%A8%E6%B7%98%E6%B1%B0%23&Refer=top","text":"日本乒乓男单选手全部淘汰","count":4057122},{"url":"/weibo?q=%E6%97%A5%E6%9C%AC%E9%87%91%E7%89%8C&Refer=top","text":"日本金牌","count":4047787.1999999997},{"url":"/weibo?q=%23%E5%8E%9F%E6%9D%A5%E8%B7%B3%E6%B0%B4%E6%8C%BA%E8%B4%B9%E6%95%99%E7%BB%83%E7%9A%84%23&Refer=top","text":"原来跳水挺费教练的","count":4000327.1999999997},{"url":"/weibo?q=%23%E6%B0%B4%E8%B0%B7%E9%9A%BC%E5%90%B9%E7%90%83%23&Refer=top","text":"水谷隼吹球","count":3946677.5999999996},{"url":"/weibo?q=%23%E7%8E%8B%E4%B8%BD%E4%B8%BD%E5%A5%BD%E5%BC%BA%23&Refer=top","text":"王丽丽好强","count":3896287.1999999997},{"url":"/weibo?q=%23%E4%B8%8A%E6%B5%B7%E7%96%AB%E6%83%85%23&Refer=top","text":"上海疫情","count":3759859.1999999997},{"url":"/weibo?q=%23%E6%8B%9C%E5%B0%94%E6%96%AF%E5%A5%B3%E5%9B%A2%E9%80%80%E8%B5%9B%23&Refer=top","text":"拜尔斯女团退赛","count":3660313.1999999997},{"url":"/weibo?q=%23%E5%8D%97%E4%BA%AC%E7%96%AB%E6%83%85%E6%AF%92%E6%A0%AA%E4%B8%BA%E5%BE%B7%E5%B0%94%E5%A1%94%E6%AF%92%E6%A0%AA%23&Refer=top","text":"南京疫情毒株为德尔塔毒株","count":3646160.4},{"url":"/weibo?q=%23%E8%AE%B8%E6%98%95%E7%A7%B0%E8%B5%9E%E4%BC%8A%E8%97%A4%E7%BE%8E%E8%AF%9A%23&Refer=top","text":"许昕称赞伊藤美诚","count":3481329.6},{"url":"/weibo?q=%23%E9%A9%AC%E9%BE%99VS%E8%A5%BF%E8%92%99%E9%AB%98%E8%8C%A8%23&Refer=top","text":"马龙VS西蒙高茨","count":3451284},{"url":"/weibo?q=%23%E5%AD%99%E9%A2%96%E8%8E%8E%E5%87%BA%E6%88%98%E4%B9%92%E4%B9%93%E7%90%83%E5%A5%B3%E5%8D%95%23&Refer=top","text":"孙颖莎出战乒乓球女单","count":3208186.8},{"url":"/weibo?q=%23%E6%8B%9C%E5%B0%94%E6%96%AF%E5%A4%B1%E8%AF%AF%23&Refer=top","text":"拜尔斯失误","count":3185962.8},{"url":"/weibo?q=%23%E5%AD%99%E9%A2%96%E8%8E%8E4%E6%AF%940%E6%99%8B%E7%BA%A716%E5%BC%BA%23&Refer=top","text":"孙颖莎4比0晋级16强","count":3184033.1999999997},{"url":"/weibo?q=%E5%BC%A0%E6%9C%AC%E6%99%BA%E5%92%8C%E5%A3%B0%E9%9F%B3%E5%A5%BD%E5%A4%A7&Refer=top","text":"张本智和声音好大","count":3162686.4},{"url":"/weibo?q=%23%E6%9D%A8%E5%80%A9%E6%9D%A8%E7%9A%93%E7%84%B6%E6%99%8B%E7%BA%A7%E6%B0%94%E6%AD%A5%E6%9E%AA%E6%B7%B7%E5%9B%A2%E5%86%B3%E8%B5%9B%23&Refer=top","text":"杨倩杨皓然晋级气步枪混团决赛","count":3147933},{"url":"/weibo?q=%23%E7%AB%9E%E6%8A%80%E4%BD%93%E6%93%8D%E5%A5%B3%E5%AD%90%E5%9B%A2%E4%BD%93%E5%86%B3%E8%B5%9B%23&Refer=top","text":"竞技体操女子团体决赛","count":3093433.1999999997},{"url":"/weibo?q=%23%E5%88%98%E5%9B%BD%E6%A2%81%E6%8B%A5%E6%8A%B1%E9%A9%AC%E7%90%B3%23&Refer=top","text":"刘国梁拥抱马琳","count":3084597.6},{"url":"/weibo?q=%E5%90%B4%E7%A3%8A%E9%80%A0%E5%9E%8B%20%E4%BA%BA%E7%B1%BB%E9%AB%98%E8%B4%A8%E9%87%8F%E7%94%B7%E6%80%A7&Refer=top","text":"吴磊造型 人类高质量男性","count":3044239.1999999997},{"url":"/weibo?q=%23%E4%BD%86%E6%96%8C%E5%86%8D%E9%81%93%E6%AD%89%23&Refer=top","text":"但斌再道歉","count":3032625.6},{"url":"/weibo?q=%23%E9%82%93%E4%BA%9A%E8%90%8D%E5%A4%8D%E7%9B%98%E5%A5%A5%E8%BF%90%E6%B7%B7%E5%8F%8C%E5%86%B3%E8%B5%9B%23&Refer=top","text":"邓亚萍复盘奥运混双决赛","count":3001790.4},{"url":"/weibo?q=%23%E6%9D%A8%E7%9A%93%E7%84%B6%E5%AE%9E%E7%8E%B0%E5%A4%A7%E6%BB%A1%E8%B4%AF%23&Refer=top","text":"杨皓然实现大满贯","count":2972479.1999999997}]