[{"url":"/weibo?q=%E5%90%B4%E5%AD%9F%E8%BE%BE%E6%82%A3%E8%82%9D%E7%99%8C&Refer=top","text":"吴孟达患肝癌","count":5161753.2},{"url":"/weibo?q=%23%E7%BD%91%E5%8F%8B%E5%81%B6%E9%81%87%E6%92%92%E8%B4%9D%E5%AE%81%E4%B8%80%E5%AE%B6%E5%9B%9B%E5%8F%A3%23&Refer=top","text":"网友偶遇撒贝宁一家四口","count":4843008},{"url":"/weibo?q=%E7%94%B7%E5%AD%90%E5%85%A5%E8%81%8C2%E5%B0%8F%E6%97%B6%E7%8C%9D%E6%AD%BB&Refer=top","text":"男子入职2小时猝死","count":4781889.6},{"url":"/weibo?q=%23%E4%B8%AD%E5%A4%AE%E4%B8%80%E5%8F%B7%E6%96%87%E4%BB%B6%E5%BC%BA%E8%B0%83%E6%89%93%E8%B5%A2%E7%A7%8D%E4%B8%9A%E7%BF%BB%E8%BA%AB%E4%BB%97%23&Refer=top","text":"中央一号文件强调打赢种业翻身仗","count":4275860.399999999},{"url":"/weibo?q=%23%E6%88%91%E5%9B%BD%E4%BB%8D%E4%BF%9D%E7%95%99%E7%9D%8081%E5%AF%B9%E6%89%B6%E8%B4%AB%E5%B0%8F%E6%85%A2%E8%BD%A6%23&Refer=top","text":"我国仍保留着81对扶贫小慢车","count":4231893.6},{"url":"/weibo?q=%23%E9%9F%A9%E5%9B%BD%E7%BD%91%E5%8F%8B%E7%A7%B0%E6%B1%9F%E7%96%8F%E5%BD%B1%E6%98%AF%E9%9F%A9%E5%9B%BD%E5%90%8D%E5%AD%97%23&Refer=top","text":"韩国网友称江疏影是韩国名字","count":4038192},{"url":"/weibo?q=%23%E7%8C%9D%E6%AD%BB%E6%9C%89%E8%BF%99%E4%BA%9B%E8%BA%AB%E4%BD%93%E4%BF%A1%E5%8F%B7%23&Refer=top","text":"猝死有这些身体信号","count":3634629.6},{"url":"/weibo?q=%23%E5%BC%A0%E5%B0%8F%E6%96%90%E8%B7%AF%E6%BC%94%E6%9C%8D%E8%A3%85%E5%93%81%E7%89%8C%E5%8F%98%E5%8C%96%23&Refer=top","text":"张小斐路演服装品牌变化","count":3046808.4},{"url":"/weibo?q=%23%E8%A5%BF%E8%97%8F%E5%86%92%E9%99%A9%E7%8E%8B%E7%8E%8B%E7%9B%B8%E5%86%9B%E7%B3%BB%E6%84%8F%E5%A4%96%E8%90%BD%E6%B0%B4%23&Refer=top","text":"西藏冒险王王相军系意外落水","count":2783841.6},{"url":"/weibo?q=%23%E4%B8%A5%E7%A6%81%E5%9F%8E%E9%87%8C%E4%BA%BA%E5%88%A9%E7%94%A8%E5%86%9C%E6%9D%91%E5%AE%85%E5%9F%BA%E5%9C%B0%E5%BB%BA%E5%88%AB%E5%A2%85%E4%BC%9A%E9%A6%86%23&Refer=top","text":"严禁城里人利用农村宅基地建别墅会馆","count":2670181},{"url":"/weibo?q=%23%E7%A8%8B%E8%8E%89%E8%8E%8E%E5%90%91%E5%90%89%E5%85%8B%E9%9A%BD%E9%80%B8%E9%81%93%E6%AD%89%23&Refer=top","text":"程莉莎向吉克隽逸道歉","count":2661200.4},{"url":"/weibo?q=%2323%E5%B2%81%E5%A5%B3%E7%94%9F%E5%9C%A8%E8%B4%A7%E6%8B%89%E6%8B%89%E8%BD%A6%E4%B8%8A%E8%B7%B3%E7%AA%97%E8%BA%AB%E4%BA%A1%23&Refer=top","text":"23岁女生在货拉拉车上跳窗身亡","count":2615359.2},{"url":"/weibo?q=%E9%AD%8F%E5%AE%8F%E5%AE%87&Refer=top","text":"魏宏宇","count":2580188.4},{"url":"/weibo?q=%E6%B1%9F%E7%96%8F%E5%BD%B1%E7%94%A8%E8%AF%97%E5%8F%A5%E5%9B%9E%E5%BA%94%E9%9F%A9%E5%9B%BD%E7%BD%91%E5%8F%8B&Refer=top","text":"江疏影用诗句回应韩国网友","count":2552449},{"url":"/weibo?q=%E5%90%B4%E5%AD%9F%E8%BE%BE&Refer=top","text":"吴孟达","count":2517325.1999999997},{"url":"/weibo?q=%23%E6%96%B0%E5%86%A0%E7%96%AB%E8%8B%97%E6%8E%A5%E7%A7%8D%E8%AF%81%E6%98%8E%E8%83%BD%E6%9B%BF%E4%BB%A3%E6%A0%B8%E9%85%B8%E6%8A%A5%E5%91%8A%E5%90%97%23&Refer=top","text":"新冠疫苗接种证明能替代核酸报告吗","count":2231408},{"url":"/weibo?q=%23%E7%88%B1%E5%A5%87%E8%89%BA%E5%91%98%E5%B7%A5%E8%90%BD%E6%88%B7%E5%8C%97%E4%BA%AC%E5%90%8E%E7%A6%BB%E8%81%8C%E8%A2%AB%E5%88%A4%E8%B5%9410%E4%B8%87%23&Refer=top","text":"爱奇艺员工落户北京后离职被判赔10万","count":2229253.1999999997},{"url":"/weibo?q=%23%E4%BD%A0%E5%A5%BD%E6%9D%8E%E7%84%95%E8%8B%B1%E7%A5%A8%E6%88%BF%E7%A0%B441%E4%BA%BF%23&Refer=top","text":"你好李焕英票房破41亿","count":2186695.1999999997},{"url":"/weibo?q=%E9%9F%A9%E7%BE%8E%E5%A8%9F%E5%8F%91%E9%99%85%E7%BA%BF&Refer=top","text":"韩美娟发际线","count":2130708},{"url":"/weibo?q=%23%E8%B4%BE%E7%8E%B2%E9%AB%98%E6%83%85%E5%95%86%E5%BA%94%E5%AF%B9%E5%82%AC%E5%A9%9A%23&Refer=top","text":"贾玲高情商应对催婚","count":2007129},{"url":"/weibo?q=%E8%B4%A7%E6%8B%89%E6%8B%89%E5%9B%9E%E5%BA%94%E5%A5%B3%E5%AD%90%E8%B7%B3%E7%AA%97%E8%BA%AB%E4%BA%A1&Refer=top","text":"货拉拉回应女子跳窗身亡","count":1965278.4},{"url":"/weibo?q=%23%E6%9C%89%E8%BF%87%E6%95%8F%E6%80%A7%E9%BC%BB%E7%82%8E%E5%8F%AF%E6%8E%A5%E7%A7%8D%E6%96%B0%E5%86%A0%E7%96%AB%E8%8B%97%E5%90%97%23&Refer=top","text":"有过敏性鼻炎可接种新冠疫苗吗","count":1946924.4},{"url":"/weibo?q=%E5%9F%BA%E9%87%91&Refer=top","text":"基金","count":1943853.5999999999},{"url":"/weibo?q=%23%E8%B4%B5%E5%B7%9E%E5%8F%91%E7%8E%B06.3%E4%BA%BF%E5%B9%B4%E5%89%8D%E7%9C%9F%E8%8F%8C%E7%B1%BB%E7%94%9F%E7%89%A9%E5%8C%96%E7%9F%B3%23&Refer=top","text":"贵州发现6.3亿年前真菌类生物化石","count":1939206},{"url":"/weibo?q=%E5%BC%A0%E5%B0%8F%E6%96%90%E4%B8%8B%E7%8F%AD%E5%9B%BE&Refer=top","text":"张小斐下班图","count":1905131.2000000002},{"url":"/weibo?q=%E9%87%91%E6%98%9F%E8%AF%B4%E9%9B%AA%E5%9B%BD%E5%88%97%E8%BD%A6%E5%BA%94%E8%AF%A5%E5%8F%AB%E9%9B%AA%E5%9B%BD%E9%A4%90%E8%BD%A6&Refer=top","text":"金星说雪国列车应该叫雪国餐车","count":1842440},{"url":"/weibo?q=%23%E6%B6%89%E4%BA%8B%E8%B4%A7%E6%8B%89%E6%8B%89%E5%8F%B8%E6%9C%BA%E5%B7%B2%E8%A2%AB%E9%87%8A%E6%94%BE%23&Refer=top","text":"涉事货拉拉司机已被释放","count":1795218},{"url":"/weibo?q=%E8%8C%85%E5%8F%B0%E5%A4%A7%E8%B7%8C&Refer=top","text":"茅台大跌","count":1739841.5999999999},{"url":"/weibo?q=%E5%8C%97%E4%BA%AC%E5%90%8C%E4%BB%81%E5%A0%82%E6%80%BB%E7%BB%8F%E7%90%86%E9%AB%98%E6%8C%AF%E5%9D%A4%E8%A2%AB%E6%9F%A5&Refer=top","text":"北京同仁堂总经理高振坤被查","count":1654107.5999999999},{"url":"/weibo?q=%23%E4%BD%A0%E5%A5%BD%E6%9D%8E%E7%84%95%E8%8B%B1%E7%A5%A8%E6%88%BF%E7%A0%B440%E4%BA%BF%23&Refer=top","text":"你好李焕英票房破40亿","count":1640682},{"url":"/weibo?q=%23%E5%96%9C%E6%AC%A2%E5%86%B7%E6%88%98%E7%9A%84%E4%BA%BA%E9%83%BD%E6%98%AF%E4%BB%80%E4%B9%88%E5%BF%83%E7%90%86%23&Refer=top","text":"喜欢冷战的人都是什么心理","count":1556824.8},{"url":"/weibo?q=%E9%BE%99%E4%B8%B9%E5%A6%AE%20%E9%80%89%E7%A7%80%E5%88%BB%E8%BF%9BDNA%E9%87%8C%E7%9A%84%E5%A5%B3%E4%BA%BA&Refer=top","text":"龙丹妮 选秀刻进DNA里的女人","count":1553578.8},{"url":"/weibo?q=%23%E5%8E%BB%E5%B9%B4%E5%8F%A3%E7%BA%A2%E9%94%80%E9%87%8F%E4%B8%8B%E6%BB%91%E8%BF%91%E5%8D%8A%23&Refer=top","text":"去年口红销量下滑近半","count":1394703.5999999999},{"url":"/weibo?q=%23%E5%85%A8%E8%81%8C%E5%A4%AA%E5%A4%AA%E7%A6%BB%E5%A9%9A%E8%8E%B75%E4%B8%87%E5%AE%B6%E5%8A%A1%E8%A1%A5%E5%81%BF%23&Refer=top","text":"全职太太离婚获5万家务补偿","count":1354658.4},{"url":"/weibo?q=%E6%8B%8E%E7%9D%80%E4%B8%80%E7%93%B6%E5%95%A4%E9%85%92%20%E9%BE%99%E4%B8%B9%E5%A6%AE%E8%B5%B0%E4%BA%86%E5%87%BA%E5%8E%BB&Refer=top","text":"拎着一瓶啤酒 龙丹妮走了出去","count":1347747.5999999999},{"url":"/weibo?q=%E8%96%87%E5%A8%85%20%E6%98%8E%E6%98%9F%E7%9A%84%E5%BD%92%E5%AE%BF%E9%83%BD%E6%98%AF%E5%B8%A6%E8%B4%A7&Refer=top","text":"薇娅 明星的归宿都是带货","count":1325025.5999999999},{"url":"/weibo?q=%23%E5%AD%A6%E6%A0%A1%E6%94%B6%E5%8F%96%E5%AD%A6%E7%94%9F165%E4%B8%87%E5%85%83%E9%97%A8%E7%A6%81%E5%8D%A1%E6%9C%8D%E5%8A%A1%E8%B4%B9%23&Refer=top","text":"学校收取学生165万元门禁卡服务费","count":1295157.5999999999},{"url":"/weibo?q=%23%E5%B7%B4%E8%A5%BF%E8%8C%B9%E9%A9%AC%E6%97%8F%E6%9C%80%E5%90%8E%E4%B8%80%E5%90%8D%E7%94%B7%E6%80%A7%E6%82%A3%E6%96%B0%E5%86%A0%E6%AD%BB%E4%BA%A1%23&Refer=top","text":"巴西茹马族最后一名男性患新冠死亡","count":1287308.4},{"url":"/weibo?q=%E5%BC%80%E5%AD%A6&Refer=top","text":"开学","count":1276093.2},{"url":"/weibo?q=%23%E5%B9%BF%E4%B8%9C1%E7%94%B7%E5%AD%90%E8%AF%8B%E6%AF%81%E6%88%8D%E8%BE%B9%E8%8B%B1%E9%9B%84%E8%A2%AB%E5%88%91%E6%8B%98%23&Refer=top","text":"广东1男子诋毁戍边英雄被刑拘","count":1263020.4},{"url":"/weibo?q=%23%E5%94%90%E6%8E%A23%E4%B8%AD%E5%9B%BD%E5%BD%B1%E5%8F%B2%E6%9C%80%E5%BF%AB%E7%A0%B440%E4%BA%BF%E7%94%B5%E5%BD%B1%23&Refer=top","text":"唐探3中国影史最快破40亿电影","count":1228766.4000000001},{"url":"/weibo?q=%E6%88%91%E5%9B%BD%E6%B8%A4%E6%B5%B7%E5%86%8D%E8%8E%B7%E4%BA%BF%E5%90%A8%E7%BA%A7%E6%B2%B9%E6%B0%94%E5%A4%A7%E5%8F%91%E7%8E%B0&Refer=top","text":"我国渤海再获亿吨级油气大发现","count":1202036.4},{"url":"/weibo?q=%E6%B3%B0%E5%9B%BD%E6%80%BB%E7%90%86%E5%B0%86%E7%AC%AC%E4%B8%80%E4%B8%AA%E6%8E%A5%E7%A7%8D%E4%B8%AD%E5%9B%BD%E7%96%AB%E8%8B%97&Refer=top","text":"泰国总理将第一个接种中国疫苗","count":1172395.2},{"url":"/weibo?q=%E4%B8%8A%E6%B5%B7%E5%B0%8F%E5%8C%BA%E5%AE%89%E8%A3%85%E7%8B%AC%E5%B1%85%E8%80%81%E4%BA%BA%E5%85%AD%E4%BB%B6%E5%A5%97&Refer=top","text":"上海小区安装独居老人六件套","count":1129914},{"url":"/weibo?q=%23%E5%AE%B6%E5%B1%9E%E5%9B%9E%E5%BA%94%E5%A5%B3%E5%AD%A9%E8%B7%B3%E8%B4%A7%E6%8B%89%E6%8B%89%E8%BD%A6%E7%AA%97%E8%BA%AB%E4%BA%A1%23&Refer=top","text":"家属回应女孩跳货拉拉车窗身亡","count":1100127.5999999999},{"url":"/weibo?q=%23%E8%8B%8F%E9%94%A6%E5%84%BF%E6%99%8B%E5%8D%87%E8%B4%B5%E5%A6%83%23&Refer=top","text":"苏锦儿晋升贵妃","count":1031010},{"url":"/weibo?q=%E5%8D%96%E7%9A%84%E4%B8%8D%E6%98%AF%E6%B0%94%E7%90%83%20%E6%98%AF%E5%AF%B9%E7%94%9F%E6%B4%BB%E7%9A%84%E5%B8%8C%E6%9C%9B&Refer=top","text":"卖的不是气球 是对生活的希望","count":1009296},{"url":"/weibo?q=%E6%9D%8E%E6%A0%B9%E7%A6%BB%E5%A9%9A&Refer=top","text":"李根离婚","count":992392.7999999999},{"url":"/weibo?q=%E7%9C%8B%E8%B5%98%E5%A9%BF%E6%9C%89%E8%A2%AB%E7%88%BD%E5%88%B0&Refer=top","text":"看赘婿有被爽到","count":967385.6000000001},{"url":"/weibo?q=%23%E9%83%91%E4%B9%83%E9%A6%A8%E8%AF%B4%E9%B8%A1%E7%9A%AE%E7%96%99%E7%98%A9%E6%98%AF%E7%9A%AE%E6%AF%9B%E5%98%AD%E8%B5%B7%E6%9D%A5%23&Refer=top","text":"郑乃馨说鸡皮疙瘩是皮毛嘭起来","count":966175.2}]